<?xml version="1.0" encoding="UTF-8"?>
<?xml-model http://music-encoding.org/schema/4.0.0/mei-all.rng application/xml http://relaxng.org/ns/structure/1.0?><?xml-model http://music-encoding.org/schema/4.0.0/mei-all.rng application/xml http://purl.oclc.org/dsdl/schematron?><mei xmlns="http://www.music-encoding.org/ns/mei" meiversion="4.0.0" xml:id="work_00064">
   <meiHead>
      <fileDesc>
         <titleStmt>
            <title/>
         </titleStmt>
         <pubStmt>
            <unpub/>
         </pubStmt>
         <sourceDesc>
            <source/>
         </sourceDesc>
      </fileDesc>
      <workList>
         <work type="vocal collection">
            <identifier type="opus" n="64"/>
            <title type="main" xml:id="work_00064_title"/>
            <composer>
               <persName/>
            </composer>
            <arranger>
               <persName/>
            </arranger>
            <editor/>
            <creation/>
            <history>
               <eventList>
                  <event type="publication">
                     <date/>
                  </event>
               </eventList>
            </history>
            <langUsage>
               <language/>
            </langUsage>
            <perfMedium>
               <perfResList>
                  <perfRes/>
               </perfResList>
            </perfMedium>
            <notesStmt>
               <annot/>
            </notesStmt>
            <expressionList>
               <expression>
                  <title corresp="#work_00064_title"/>
               </expression>
            </expressionList>
            <componentList>
               <work type="" n="001" corresp="#work_00064_001">
                  <identifier type="no">1</identifier>
                  <title xml:lang="de" corresp="#work_00064_001_title">
                     <titlePart type="main">Klage</titlePart>
                  </title>
               </work>
               <work type="" n="002" corresp="#work_00064_002">
                  <identifier type="no">2</identifier>
                  <title xml:lang="de" corresp="#work_00064_002_title">
                     <titlePart type="main">Gut‘ Nacht</titlePart>
                  </title>
               </work>
               <work type="" n="003" corresp="#work_00064_003">
                  <identifier type="no">3</identifier>
                  <title xml:lang="de" corresp="#work_00064_003_title">
                     <titlePart type="main">Wohin mit der Freud</titlePart>
                  </title>
               </work>
               <work type="" n="004" corresp="#work_00064_004">
                  <identifier type="no">4</identifier>
                  <title xml:lang="de" corresp="#work_00064_004_title">
                     <titlePart type="main">Untreue</titlePart>
                  </title>
               </work>
               <work type="" n="005" corresp="#work_00064_005">
                  <identifier type="no">5</identifier>
                  <title xml:lang="de" corresp="#work_00064_005_title">
                     <titlePart type="main">Des Buben Herzeleid</titlePart>
                  </title>
               </work>
               <work type="" n="006" corresp="#work_00064_006">
                  <identifier type="no">6</identifier>
                  <title xml:lang="de" corresp="#work_00064_006_title">
                     <titlePart type="main">Mei Maidle</titlePart>
                  </title>
               </work>
               <work type="" n="007" corresp="#work_00064_007">
                  <identifier type="no">7</identifier>
                  <title xml:lang="de" corresp="#work_00064_007_title">
                     <titlePart type="main">O Tannenbaum!</titlePart>
                  </title>
               </work>
               <work type="" n="008" corresp="#work_00064_008">
                  <identifier type="no">8</identifier>
                  <title xml:lang="de" corresp="#work_00064_008_title">
                     <titlePart type="main">Treue</titlePart>
                  </title>
               </work>
               <work type="" n="009" corresp="#work_00064_009">
                  <identifier type="no">9</identifier>
                  <title xml:lang="de" corresp="#work_00064_009_title">
                     <titlePart type="main">Wenn ich an den letzten Abend denk</titlePart>
                  </title>
               </work>
               <work type="" n="010" corresp="#work_00064_010">
                  <identifier type="no">10</identifier>
                  <title xml:lang="de" corresp="#work_00064_010_title">
                     <titlePart type="main">Soldatenlied</titlePart>
                  </title>
               </work>
               <work type="" n="011" corresp="#work_00064_011">
                  <identifier type="no">11</identifier>
                  <title xml:lang="de" corresp="#work_00064_011_title">
                     <titlePart type="main">Liebe um Liebe</titlePart>
                  </title>
               </work>
               <work type="" n="012" corresp="#work_00064_012">
                  <identifier type="no">12</identifier>
                  <title xml:lang="de" corresp="#work_00064_012_title">
                     <titlePart type="main">Frühling</titlePart>
                  </title>
               </work>
            </componentList>
         </work>
      </workList>
      <manifestationList>
         <manifestation/>
      </manifestationList>
   </meiHead>
   <music>
      <facsimile/>
      <body>
         <mdiv n="1" corresp="#work_00064_001"/>
         <mdiv n="2" corresp="#work_00064_002"/>
         <mdiv n="3" corresp="#work_00064_003"/>
         <mdiv n="4" corresp="#work_00064_004"/>
         <mdiv n="5" corresp="#work_00064_005"/>
         <mdiv n="6" corresp="#work_00064_006"/>
         <mdiv n="7" corresp="#work_00064_007"/>
         <mdiv n="8" corresp="#work_00064_008"/>
         <mdiv n="9" corresp="#work_00064_009"/>
         <mdiv n="10" corresp="#work_00064_010"/>
         <mdiv n="11" corresp="#work_00064_011"/>
         <mdiv n="12" corresp="#work_00064_012"/>
      </body>
   </music>
</mei>